myapp/__init__.py
myapp/justmodule.py
py_yr_common_lib-1.1.0.dist-info/DESCRIPTION.rst
py_yr_common_lib-1.1.0.dist-info/METADATA
py_yr_common_lib-1.1.0.dist-info/RECORD
py_yr_common_lib-1.1.0.dist-info/WHEEL
py_yr_common_lib-1.1.0.dist-info/metadata.json
py_yr_common_lib-1.1.0.dist-info/top_level.txt
