Metadata-Version: 2.0
Name: py-yr-common-lib
Version: 1.1.0
Summary: Useful towel-related stuff.
Home-page: http://pypi.python.org/pypi/MyApplication_v010/
Author: name surname
Author-email: oren.razon@myyellowroad.com
License: UNKNOWN
Platform: UNKNOWN
